colcon_ros/__init__.py
colcon_ros/installed_packages.py
colcon_ros/argcomplete_completer/__init__.py
colcon_ros/argcomplete_completer/catkin_cmake_args.py
colcon_ros/package_augmentation/__init__.py
colcon_ros/package_augmentation/ros_ament_index.py
colcon_ros/package_augmentation/ros_ament_python.py
colcon_ros/package_identification/__init__.py
colcon_ros/package_identification/ignore.py
colcon_ros/package_identification/ros.py
colcon_ros/prefix_path/__init__.py
colcon_ros/prefix_path/ament.py
colcon_ros/prefix_path/catkin.py
colcon_ros/task/__init__.py
colcon_ros/task/ament_cmake/__init__.py
colcon_ros/task/ament_cmake/build.py
colcon_ros/task/ament_cmake/test.py
colcon_ros/task/ament_python/__init__.py
colcon_ros/task/ament_python/build.py
colcon_ros/task/ament_python/test.py
colcon_ros/task/catkin/__init__.py
colcon_ros/task/catkin/build.py
colcon_ros/task/catkin/test.py
colcon_ros/task/cmake/__init__.py
colcon_ros/task/cmake/build.py
colcon_ros/task/cmake/test.py
colcon_ros-0.5.0.dist-info/LICENSE
colcon_ros-0.5.0.dist-info/METADATA
colcon_ros-0.5.0.dist-info/WHEEL
colcon_ros-0.5.0.dist-info/entry_points.txt
colcon_ros-0.5.0.dist-info/top_level.txt
colcon_ros-0.5.0.dist-info/zip-safe
colcon_ros-0.5.0.dist-info/RECORD
